rapid/__init__.py
rapid/cli/__init__.py
rapid/core/__init__.py
rapid/core/app.py
rapid/enterprise/__init__.py
rapid/enterprise/business_intelligence.py
rapid/enterprise/load_balancer.py
rapid/enterprise/monitoring.py
rapid/enterprise/response.py
rapid/enterprise/server.py
rapid/enterprise/tenant.py
rapid/financial/__init__.py
rapid/gaming/__init__.py
rapid/government/__init__.py
rapid/government/audit.py
rapid/government/compliance.py
rapid/government/crypto.py
rapid/government/security.py
rapid/government/server.py
rapid/http/__init__.py
rapid/http/request.py
rapid/http/response.py
rapid/routing/__init__.py
rapid/routing/matcher.py
rapid/routing/route.py
rapid/routing/router.py
rapid/server/__init__.py
rapid/server/dev_server.py
rapid/server/websocket.py
rapid/utils/__init__.py
rapid/utils/json.py
rapid/utils/memory.py
rapid/video/__init__.py
rapid_web_api-1.0.1.dist-info/licenses/LICENSE
rapid_web_api-1.0.1.dist-info/METADATA
rapid_web_api-1.0.1.dist-info/WHEEL
rapid_web_api-1.0.1.dist-info/top_level.txt
rapid_web_api-1.0.1.dist-info/RECORD
