Metadata-Version: 2.4
Name: rapid-web-api
Version: 1.0.1
Summary: High-performance Python web framework - FastAPI compatible with 2x performance improvements
Home-page: https://github.com/wesellis/rapid
Author: Wes Ellis
Author-email: Wes Ellis <wes@example.com>
License: MIT
Project-URL: Homepage, https://github.com/wesellis/rapid
Project-URL: Documentation, https://wesellis.github.io/rapid
Project-URL: Repository, https://github.com/wesellis/rapid
Project-URL: Issues, https://github.com/wesellis/rapid/issues
Classifier: Development Status :: 5 - Production/Stable
Classifier: Intended Audience :: Developers
Classifier: Operating System :: OS Independent
Classifier: Programming Language :: Python :: 3
Classifier: Programming Language :: Python :: 3.8
Classifier: Programming Language :: Python :: 3.9
Classifier: Programming Language :: Python :: 3.10
Classifier: Programming Language :: Python :: 3.11
Classifier: Programming Language :: Python :: 3.12
Classifier: Topic :: Internet :: WWW/HTTP :: HTTP Servers
Classifier: Topic :: Software Development :: Libraries :: Python Modules
Requires-Python: >=3.8
License-File: LICENSE
Requires-Dist: starlette>=0.27.0
Requires-Dist: pydantic>=2.0.0
Requires-Dist: uvicorn[standard]>=0.18.0
Provides-Extra: dev
Requires-Dist: pytest>=7.0.0; extra == "dev"
Requires-Dist: pytest-cov>=4.0.0; extra == "dev"
Requires-Dist: black>=22.0.0; extra == "dev"
Requires-Dist: isort>=5.0.0; extra == "dev"
Requires-Dist: flake8>=5.0.0; extra == "dev"
Requires-Dist: mypy>=1.0.0; extra == "dev"
Requires-Dist: pre-commit>=2.20.0; extra == "dev"
Provides-Extra: performance
Requires-Dist: orjson>=3.8.0; extra == "performance"
Requires-Dist: ujson>=5.6.0; extra == "performance"
Dynamic: license-file
